[
  {
    "id": "ATzb348tk2Sb8vf4Pm2p",
    "items": [
      {
        "totalCost": 11000,
        "quantity": 1,
        "itemId": "OFbAdoepWhY4qTcJyPjr",
        "unit": "kg",
        "previousPrice": 11000,
        "pricePerUnit": 11000,
        "itemName": "Coffe",
        "category": "Supplies"
      }
    ],
    "createdAt": "2026-06-07T04:59:30.000Z",
    "date": "2026-06-07",
    "performedByName": "Naveen",
    "supplierPhone": "0754502681",
    "paymentMethod": "credit",
    "paidDate": null,
    "performedBy": "Naveen",
    "itemsCount": 1,
    "dueDate": "2026-06-14",
    "notes": "",
    "billNumber": "12",
    "approvalNotes": "",
    "paymentStatus": "unpaid",
    "approvedBy": "Naveen",
    "approvedByName": "Naveen",
    "status": "rejected",
    "supplierId": "M3VWG7YWQ4b65RJ1Keyf",
    "supplierName": "colombo street",
    "stockUpdated": false,
    "rejectedReason": "wrong bill",
    "billTotal": 11000,
    "approvedAt": "2026-06-07T05:00:42.000Z"
  },
  {
    "id": "YVrk7TlUbqCkYNpch5O6",
    "supplierName": "colombo street",
    "stockUpdated": true,
    "returnStatus": "partially_returned",
    "date": "2026-06-07",
    "billPhotoUrl": "",
    "returnedValue": 30000,
    "createdAt": "2026-06-07T14:45:48.000Z",
    "notes": "[Resubmitted from rejected]",
    "itemsCount": 4,
    "supplierId": "M3VWG7YWQ4b65RJ1Keyf",
    "lastReturnAt": "2026-06-08T05:14:56.000Z",
    "approvalNotes": "Approved",
    "billPhotoPath": "",
    "paidNotes": "",
    "rejectedReason": "",
    "approvedAt": "2026-06-07T14:47:01.000Z",
    "billTotal": 42600,
    "performedByName": "Naveen",
    "items": [
      {
        "previousPrice": 12000,
        "itemName": "Coffe",
        "pricePerUnit": 10000,
        "category": "Supplies",
        "totalCost": 30000,
        "quantity": 3,
        "itemId": "OFbAdoepWhY4qTcJyPjr",
        "unit": "kg"
      },
      {
        "totalCost": 1000,
        "quantity": 2,
        "unit": "L",
        "itemId": "mlE18M4E7Gbi0ENBbmXC",
        "previousPrice": 475,
        "pricePerUnit": 500,
        "itemName": "Fresh Milk",
        "category": "Dairy"
      },
      {
        "quantity": 1,
        "itemId": "mlE18M4E7Gbi0ENBbmXC",
        "unit": "L",
        "totalCost": 600,
        "itemName": "Fresh Milk",
        "pricePerUnit": 600,
        "category": "Dairy",
        "previousPrice": 475
      },
      {
        "unit": "kg",
        "itemId": "OFbAdoepWhY4qTcJyPjr",
        "quantity": 1,
        "totalCost": 11000,
        "category": "Supplies",
        "itemName": "Coffe",
        "pricePerUnit": 11000,
        "previousPrice": 12000
      }
    ],
    "paidDate": null,
    "paymentMethod": "credit",
    "supplierPhone": "0754502681",
    "hasReturns": true,
    "billNumber": "12-R",
    "performedBy": "Naveen",
    "dueDate": "2026-06-14",
    "status": "approved",
    "approvedByName": "Naveen",
    "approvedBy": "Naveen",
    "paymentStatus": "unpaid"
  },
  {
    "id": "ieDJRt3OtbtyvQw4Ph1B",
    "approvalNotes": "",
    "supplierId": "M3VWG7YWQ4b65RJ1Keyf",
    "itemsCount": 2,
    "notes": "",
    "createdAt": "2026-06-07T07:50:02.000Z",
    "billPhotoUrl": "https://firebasestorage.googleapis.com/v0/b/buono-project-927b8.firebasestorage.app/o/bills%2Fbill_1780818589759_Naveen.jpg?alt=media&token=64004ca2-126f-4675-a36c-9d0b0455cd75",
    "date": "2026-06-07",
    "supplierName": "colombo street",
    "stockUpdated": false,
    "paymentStatus": "paid",
    "approvedBy": null,
    "status": "pending_approval",
    "approvedByName": null,
    "performedBy": "Naveen",
    "dueDate": null,
    "billNumber": "10",
    "supplierPhone": "0754502681",
    "paymentMethod": "cash",
    "paidDate": "2026-06-07",
    "items": [
      {
        "pricePerUnit": 11000,
        "itemName": "Coffe",
        "category": "Supplies",
        "previousPrice": 12000,
        "quantity": 1,
        "unit": "kg",
        "itemId": "OFbAdoepWhY4qTcJyPjr",
        "totalCost": 11000
      },
      {
        "quantity": 1,
        "unit": "L",
        "itemId": "mlE18M4E7Gbi0ENBbmXC",
        "totalCost": 550,
        "itemName": "Fresh Milk",
        "pricePerUnit": 550,
        "category": "Dairy",
        "previousPrice": 475
      }
    ],
    "performedByName": "Naveen",
    "billTotal": 11550,
    "approvedAt": null,
    "rejectedReason": "",
    "paidNotes": "",
    "billPhotoPath": "bills/bill_1780818589759_Naveen.jpg"
  },
  {
    "id": "qLFjsKQ8Mj6iAT95vKyD",
    "paidAt": "2026-06-07T14:43:49.000Z",
    "supplierName": "colombo street",
    "stockUpdated": true,
    "notes": "[Resubmitted from rejected bill]",
    "itemsCount": 1,
    "supplierId": "M3VWG7YWQ4b65RJ1Keyf",
    "approvalNotes": "Approved",
    "date": "2026-06-07",
    "paidBy": "Naveen",
    "createdAt": "2026-06-07T05:02:05.000Z",
    "paidNotes": "",
    "rejectedReason": "",
    "approvedAt": "2026-06-07T05:02:28.000Z",
    "paidByName": "Naveen",
    "billTotal": 23000,
    "billNumber": "12-R",
    "performedBy": "Naveen",
    "dueDate": "2026-06-14",
    "approvedByName": "Naveen",
    "status": "approved",
    "paymentStatus": "paid",
    "approvedBy": "Naveen",
    "performedByName": "Naveen",
    "items": [
      {
        "category": "Supplies",
        "itemName": "Coffe",
        "pricePerUnit": 11500,
        "previousPrice": 11000,
        "unit": "kg",
        "itemId": "OFbAdoepWhY4qTcJyPjr",
        "quantity": 2,
        "totalCost": 23000
      }
    ],
    "paidDate": "2026-06-07",
    "paymentMethod": "credit",
    "supplierPhone": "0754502681"
  },
  {
    "id": "sVQ9K6SCICytu1EsDzhp",
    "stockUpdated": true,
    "supplierName": "colombo street",
    "date": "2026-06-07",
    "billPhotoUrl": "https://firebasestorage.googleapis.com/v0/b/buono-project-927b8.firebasestorage.app/o/bills%2Fbill_1780817277480_Naveen.jpg?alt=media&token=71dfc616-a091-484a-8ee5-760080b0059d",
    "createdAt": "2026-06-07T07:28:11.000Z",
    "supplierId": "M3VWG7YWQ4b65RJ1Keyf",
    "approvalNotes": "Approved",
    "itemsCount": 1,
    "notes": "",
    "billPhotoPath": "bills/bill_1780817277480_Naveen.jpg",
    "billTotal": 12000,
    "approvedAt": "2026-06-07T07:28:55.000Z",
    "rejectedReason": "",
    "paidNotes": "",
    "paidDate": null,
    "supplierPhone": "0754502681",
    "paymentMethod": "bank",
    "performedByName": "Naveen",
    "items": [
      {
        "totalCost": 12000,
        "quantity": 1,
        "unit": "kg",
        "itemId": "OFbAdoepWhY4qTcJyPjr",
        "previousPrice": 11500,
        "itemName": "Coffe",
        "pricePerUnit": 12000,
        "category": "Supplies"
      }
    ],
    "approvedByName": "Naveen",
    "status": "approved",
    "approvedBy": "Naveen",
    "paymentStatus": "unpaid",
    "billNumber": "1",
    "dueDate": "2026-06-14",
    "performedBy": "Naveen"
  },
  {
    "id": "zbfQ6pq5j54cqGPgDoeq",
    "supplierName": "colombo street",
    "stockUpdated": true,
    "billTotal": 11950,
    "approvedAt": "2026-06-07T04:58:16.000Z",
    "rejectedReason": "",
    "paidDate": "2026-06-07",
    "supplierPhone": "0754502681",
    "paymentMethod": "cash",
    "date": "2026-06-07",
    "performedByName": "Naveen",
    "createdAt": "2026-06-07T04:43:25.000Z",
    "items": [
      {
        "pricePerUnit": 11000,
        "itemName": "Coffe",
        "category": "Supplies",
        "previousPrice": 11000,
        "quantity": 1,
        "unit": "kg",
        "itemId": "OFbAdoepWhY4qTcJyPjr",
        "totalCost": 11000
      },
      {
        "totalCost": 950,
        "quantity": 2,
        "unit": "L",
        "itemId": "mlE18M4E7Gbi0ENBbmXC",
        "previousPrice": 500,
        "pricePerUnit": 475,
        "itemName": "Fresh Milk",
        "category": "Dairy"
      }
    ],
    "approvedByName": "Naveen",
    "status": "approved",
    "supplierId": "M3VWG7YWQ4b65RJ1Keyf",
    "approvalNotes": "Approved",
    "paymentStatus": "paid",
    "approvedBy": "Naveen",
    "billNumber": "1",
    "performedBy": "Naveen",
    "itemsCount": 2,
    "dueDate": null,
    "notes": ""
  }
]